MANIFEST.in
README.md
setup.py
petroglyph/__init__.py
petroglyph/generator.py
petroglyph/logger.py
petroglyph/page.py
petroglyph/petroglyph
petroglyph/post.py
petroglyph/setup.py
petroglyph.egg-info/PKG-INFO
petroglyph.egg-info/SOURCES.txt
petroglyph.egg-info/dependency_links.txt
petroglyph.egg-info/requires.txt
petroglyph.egg-info/top_level.txt
petroglyph/skins/monoblue/home.html
petroglyph/skins/monoblue/page.html
petroglyph/skins/monoblue/post.html
petroglyph/skins/monoblue/tag.html
petroglyph/skins/monoblue/css/monoblue.css
petroglyph/skins/monoblue/css/normalize.css
petroglyph/skins/monoblue/css/prism.css
petroglyph/skins/monoblue/js/prism.js