Metadata-Version: 1.0
Name: petroglyph
Version: 0.5.0
Summary: A static blog generator
Home-page: https://github.com/polybuildr/petroglyph
Author: Vivek Ghaisas
Author-email: UNKNOWN
License: MIT
Keywords: static blog
Platform: UNKNOWN
